ensemble_forecast/__init__.py
ensemble_forecast/ensemble_forecast.py
ensemble_forecast-0.1.2.dist-info/LICENSE.txt
ensemble_forecast-0.1.2.dist-info/METADATA
ensemble_forecast-0.1.2.dist-info/WHEEL
ensemble_forecast-0.1.2.dist-info/top_level.txt
ensemble_forecast-0.1.2.dist-info/RECORD
