Metadata-Version: 2.1
Name: ensemble-forecast
Version: 0.1.2
Summary: A lightweight ensemble forecasting library combining classical and ML models.
Author: Ashay Thamankar
Author-email: ashaytesting@gmail.com
License: MIT
Keywords: forecasting,ensemble,time series,machine learning,prophet,ARIMA,SARIMA,Croston,LSTM,neural network,ETS,TBATS
Classifier: Programming Language :: Python :: 3
Classifier: License :: OSI Approved :: MIT License
Classifier: Operating System :: OS Independent
Classifier: Intended Audience :: Science/Research
Classifier: Topic :: Scientific/Engineering :: Artificial Intelligence
Classifier: Topic :: Software Development :: Libraries
Requires-Python: >=3.10
License-File: LICENSE.txt
Requires-Dist: numpy==1.24.3
Requires-Dist: pandas==2.0.3
Requires-Dist: python-dateutil==2.8.2
Requires-Dist: scipy==1.10.1
Requires-Dist: Cython==0.29.36
Requires-Dist: statsmodels==0.14.1
Requires-Dist: scikit-learn==1.3.2
Requires-Dist: pmdarima==2.0.4
Requires-Dist: tbats==1.1.3
Requires-Dist: statsforecast==1.6.0
Requires-Dist: prophet==1.1.4
Requires-Dist: tensorflow==2.13.0
